dynamic_import/__init__.py
dynamic_import/cache.py
dynamic_import/check.py
dynamic_import/extract.py
dynamic_import/importer.py
dynamic_import/module.py
dynamic_import/prep.py
dynamic_import/record.py
dynamic_import/special.py
dynamic_import/version.py
dynamic_import-2024.5.2.dist-info/LICENSE.txt
dynamic_import-2024.5.2.dist-info/METADATA
dynamic_import-2024.5.2.dist-info/WHEEL
dynamic_import-2024.5.2.dist-info/top_level.txt
dynamic_import-2024.5.2.dist-info/RECORD
