Metadata-Version: 2.1
Name: dynamic_import
Version: 2024.5.2
Summary: Let Dynamic Import handle your projects(package) import needs. Enables you to dynamically(lazily) import module as needed on run-time.
Author: Ritesh
License: Creative Commons Legal Code
Project-URL: Homepage, https://github.com/YoSTEALTH/Dynamic-Import
Project-URL: Issues, https://github.com/YoSTEALTH/Dynamic-Import/issues
Classifier: Topic :: Software Development
Classifier: License :: Public Domain
Classifier: Intended Audience :: Developers
Classifier: Operating System :: POSIX :: Linux
Classifier: Operating System :: MacOS
Classifier: Programming Language :: Python :: 3.8
Classifier: Programming Language :: Python :: 3.9
Classifier: Programming Language :: Python :: 3.10
Classifier: Programming Language :: Python :: 3.11
Classifier: Programming Language :: Python :: 3.12
Classifier: Development Status :: 5 - Production/Stable
Requires-Python: >=3.8
License-File: LICENSE.txt
